eventkit/__init__.py
eventkit/responder.py
eventkit_slack-0.2.0.dist-info/LICENSE
eventkit_slack-0.2.0.dist-info/METADATA
eventkit_slack-0.2.0.dist-info/WHEEL
eventkit_slack-0.2.0.dist-info/top_level.txt
eventkit_slack-0.2.0.dist-info/RECORD
