Metadata-Version: 2.1
Name: eventkit-slack
Version: 0.2.0
Summary: A library to handle Slack events
Home-page: https://github.com/oneor0/eventkit
Author: Dmitry Chernyshov
Author-email: oneor00@gmail.com
License: MIT
Platform: UNKNOWN
Classifier: License :: OSI Approved :: MIT License
Classifier: Programming Language :: Python
Classifier: Programming Language :: Python :: 3
Classifier: Programming Language :: Python :: 3.6
Classifier: Programming Language :: Python :: Implementation :: CPython
Classifier: Programming Language :: Python :: Implementation :: PyPy
Requires-Python: >=3.6.0
